rasterops/__init__.py
rasterops/accessors.py
rasterops/algo.py
rasterops/compute.py
rasterops/export.py
rasterops/intake.py
rasterops/rasterops.py
rasterops/storage.py
rasterops-0.1.5.dist-info/METADATA
rasterops-0.1.5.dist-info/WHEEL
rasterops-0.1.5.dist-info/top_level.txt
rasterops-0.1.5.dist-info/RECORD
