Metadata-Version: 2.2
Name: rasterops
Version: 0.1.5
Summary: A package for creating and managing datacubes for coastal resilience analysis.
Author-email: Chris Lowrie <lowriechris779@gmail.com>
License: MIT
Classifier: Programming Language :: Python :: 3
Classifier: License :: OSI Approved :: MIT License
Classifier: Operating System :: OS Independent
Requires-Python: <3.13,>=3.12
Requires-Dist: geospatial-analysis-environment>=0.1.12
Requires-Dist: coastal-resilience-utilities>=0.1.33
Requires-Dist: python-dotenv
Requires-Dist: s3fs
